setup.py
SHICTHRSECThread/__init__.py
SHICTHRSECThread.egg-info/PKG-INFO
SHICTHRSECThread.egg-info/SOURCES.txt
SHICTHRSECThread.egg-info/dependency_links.txt
SHICTHRSECThread.egg-info/not-zip-safe
SHICTHRSECThread.egg-info/requires.txt
SHICTHRSECThread.egg-info/top_level.txt