Metadata-Version: 2.4
Name: SHICTHRSECThread
Version: 1.0.0
Summary: SHICTHRS browser history reader
Home-page: https://github.com/JNTMTMTM/SHICTHRS_ECThread
Author: SHICTHRS
Author-email: contact@shicthrs.com
License: GPL-3.0
Requires-Dist: colorama==0.4.6
Dynamic: author
Dynamic: author-email
Dynamic: home-page
Dynamic: license
Dynamic: requires-dist
Dynamic: summary
